sndr/__init__.py
sndr/req.py
sndr-0.1.2.dist-info/METADATA
sndr-0.1.2.dist-info/RECORD
sndr-0.1.2.dist-info/WHEEL
sndr-0.1.2.dist-info/top_level.txt
